Metadata-Version: 2.1
Name: mina-distributions
Version: 0.2
Summary: Gaussian distributions
License-File: license.txt
